tax/__init__.py
tax/invoice/__init__.py
tax/invoice/client.py
tax/invoice/api/__init__.py
tax/invoice/api/auth.py
tax/invoice/api/face.py
tax/invoice/api/invoice.py
tax/invoice/utils/__init__.py
tax/invoice/utils/http.py
tax/invoice/utils/other.py
tax/invoice/utils/signature.py
tax_invoice-1.0.10.dist-info/licenses/LICENSE
tax_invoice-1.0.10.dist-info/METADATA
tax_invoice-1.0.10.dist-info/WHEEL
tax_invoice-1.0.10.dist-info/top_level.txt
tax_invoice-1.0.10.dist-info/RECORD
