Metadata-Version: 2.4
Name: tax-invoice
Version: 1.0.10
Summary: 发票SDK Python 电子发票/数电发票/全电发票/数电票/开票
Home-page: https://github.com/fapiaoapi/invoice-python-sdk
Author: yuejianghe
Author-email: yuejianghe@qq.com
Classifier: Programming Language :: Python :: 3
Classifier: License :: OSI Approved :: MIT License
Classifier: Operating System :: OS Independent
Requires-Python: >=3.6
License-File: LICENSE
Requires-Dist: requests>=2.25.0
Dynamic: author
Dynamic: author-email
Dynamic: classifier
Dynamic: description
Dynamic: description-content-type
Dynamic: home-page
Dynamic: license-file
Dynamic: requires-dist
Dynamic: requires-python
Dynamic: summary
